scripts/validate_a2a_agent.py
scripts/validate_agent.py
tests/test_tunnel.py
tunnel_manager/__init__.py
tunnel_manager/__main__.py
tunnel_manager/mcp_config.json
tunnel_manager/middlewares.py
tunnel_manager/tunnel_manager.py
tunnel_manager/tunnel_manager_agent.py
tunnel_manager/tunnel_manager_mcp.py
tunnel_manager/utils.py
tunnel_manager/skills/remote-access/SKILL.md
tunnel_manager-1.0.20.dist-info/licenses/LICENSE
tunnel_manager-1.0.20.dist-info/METADATA
tunnel_manager-1.0.20.dist-info/WHEEL
tunnel_manager-1.0.20.dist-info/entry_points.txt
tunnel_manager-1.0.20.dist-info/top_level.txt
tunnel_manager-1.0.20.dist-info/RECORD
